expyriments/__init__.py
expyriments/_about.py
expyriments/_cli.py
expyriments/client/__init__.py
expyriments/server/__init__.py
expyriments/server/api.py
expyriments/server/api_utils.py
expyriments/server/config.py
expyriments/server/generate-openapi-specs.py
expyriments/server/static_webapp/asset-manifest.json
expyriments/server/static_webapp/favicon.ico
expyriments/server/static_webapp/index.html
expyriments/server/static_webapp/logo192.png
expyriments/server/static_webapp/logo512.png
expyriments/server/static_webapp/manifest.json
expyriments/server/static_webapp/robots.txt
expyriments/server/static_webapp/static/css/main.41541bfa.chunk.css
expyriments/server/static_webapp/static/css/main.41541bfa.chunk.css.map
expyriments/server/static_webapp/static/js/2.6558af55.chunk.js
expyriments/server/static_webapp/static/js/2.6558af55.chunk.js.LICENSE.txt
expyriments/server/static_webapp/static/js/2.6558af55.chunk.js.map
expyriments/server/static_webapp/static/js/3.567aa13b.chunk.js
expyriments/server/static_webapp/static/js/3.567aa13b.chunk.js.LICENSE.txt
expyriments/server/static_webapp/static/js/3.567aa13b.chunk.js.map
expyriments/server/static_webapp/static/js/4.a82a526b.chunk.js
expyriments/server/static_webapp/static/js/4.a82a526b.chunk.js.LICENSE.txt
expyriments/server/static_webapp/static/js/4.a82a526b.chunk.js.map
expyriments/server/static_webapp/static/js/5.75c4fe93.chunk.js
expyriments/server/static_webapp/static/js/5.75c4fe93.chunk.js.LICENSE.txt
expyriments/server/static_webapp/static/js/5.75c4fe93.chunk.js.map
expyriments/server/static_webapp/static/js/6.050acb86.chunk.js
expyriments/server/static_webapp/static/js/6.050acb86.chunk.js.map
expyriments/server/static_webapp/static/js/main.d3690205.chunk.js
expyriments/server/static_webapp/static/js/main.d3690205.chunk.js.map
expyriments/server/static_webapp/static/js/runtime-main.fecdd7e3.js
expyriments/server/static_webapp/static/js/runtime-main.fecdd7e3.js.map
expyriments-0.1.2.dist-info/LICENSE
expyriments-0.1.2.dist-info/METADATA
expyriments-0.1.2.dist-info/WHEEL
expyriments-0.1.2.dist-info/entry_points.txt
expyriments-0.1.2.dist-info/top_level.txt
expyriments-0.1.2.dist-info/RECORD
